a2y_ats.cp38-win_amd64.pyd
a2y_ats-1.2.7.dist-info/LICENSE
a2y_ats-1.2.7.dist-info/METADATA
a2y_ats-1.2.7.dist-info/WHEEL
a2y_ats-1.2.7.dist-info/top_level.txt
a2y_ats-1.2.7.dist-info/RECORD
