Metadata-Version: 2.1
Name: a2y-ats
Version: 1.2.7
Summary: A module that implements an Auto Test System.
Home-page: http://www.kersci.com/a2y/ats.html
Author: Yu Han
Author-email: hanjunyu@163.com
License: Private
Platform: Windows
Platform: Linux
Classifier: Development Status :: 4 - Beta
Classifier: Intended Audience :: Developers
Classifier: License :: Free For Educational Use
Classifier: Programming Language :: Python :: 3.6
Classifier: Operating System :: Microsoft :: Windows :: Windows 10
Classifier: Operating System :: POSIX :: Linux
Requires-Dist: a2y-atsui >=0.9.6
Requires-Dist: a2y-wxtools
Requires-Dist: a2y-testparameters
Requires-Dist: a2y-paratree
Requires-Dist: a2y-handy
Requires-Dist: a2y-matplot
Requires-Dist: a2y-touch
Requires-Dist: openpyxl
